CONTRIBUTORS.txt
LICENSE.txt
MANIFEST.in
README.rst
requirements.txt
setup.py
billing/__init__.py
billing/admin.py
billing/gateway.py
billing/integration.py
billing/signals.py
billing/views.py
billing/forms/__init__.py
billing/forms/authorize_net_forms.py
billing/forms/braintree_payments_forms.py
billing/forms/eway_au_forms.py
billing/forms/paylane_forms.py
billing/forms/paypal_forms.py
billing/forms/pin_forms.py
billing/forms/stripe_forms.py
billing/forms/world_pay_forms.py
billing/gateways/__init__.py
billing/gateways/authorize_net_gateway.py
billing/gateways/beanstream_gateway.py
billing/gateways/bitcoin_gateway.py
billing/gateways/braintree_payments_gateway.py
billing/gateways/chargebee_gateway.py
billing/gateways/pay_pal_gateway.py
billing/gateways/paylane_gateway.py
billing/gateways/pin_gateway.py
billing/gateways/stripe_gateway.py
billing/gateways/we_pay_gateway.py
billing/gateways/eway_gateway/__init__.py
billing/gateways/eway_gateway/eway_gateway.py
billing/gateways/eway_gateway/eway_api/__init__.py
billing/gateways/eway_gateway/eway_api/client.py
billing/gateways/eway_gateway/eway_api/tests.py
billing/integrations/__init__.py
billing/integrations/amazon_fps_integration.py
billing/integrations/authorize_net_dpm_integration.py
billing/integrations/braintree_payments_integration.py
billing/integrations/eway_au_integration.py
billing/integrations/google_checkout_integration.py
billing/integrations/ogone_payments_integration.py
billing/integrations/pay_pal_integration.py
billing/integrations/stripe_integration.py
billing/integrations/world_pay_integration.py
billing/management/__init__.py
billing/management/commands/__init__.py
billing/management/commands/check_billing_settings.py
billing/models/__init__.py
billing/models/amazon_fps_models.py
billing/models/authorize_models.py
billing/models/eway_models.py
billing/models/gc_models.py
billing/models/paylane_models.py
billing/models/pin_models.py
billing/models/world_pay_models.py
django_merchant.egg-info/PKG-INFO
django_merchant.egg-info/SOURCES.txt
django_merchant.egg-info/dependency_links.txt
django_merchant.egg-info/not-zip-safe
django_merchant.egg-info/top_level.txt
