Metadata-Version: 1.1
Name: django-merchant
Version: 0.1
Summary: A Django app that provides helpers for multiple pluggable payment backends.
Home-page: http://github.com/agiliq/merchant
Author: Agiliq Solutions
Author-email: hello@agiliq.com
License: BSD
Platform: UNKNOWN
Classifier: Development Status :: 3 - Alpha
Classifier: Environment :: Web Environment
Classifier: Intended Audience :: Developers
Classifier: License :: OSI Approved :: BSD License
Classifier: Operating System :: OS Independent
Classifier: Programming Language :: Python
Classifier: Framework :: Django
